{
  "users": [
    {
      "email": "danny@mail.com",
      "fname": "Danny",
      "lname": "Böhm",
      "password": "test12345",
      "avatar": "https://robohash.org/ph38?set=set4",
      "ticketIds": [
        "OdBbzfo"
      ],
      "isadmin": true,
      "isloggedin": true,
      "id": 1
    },
    {
      "email": "michelle@mail.com",
      "fname": "Michelle",
      "lname": "Sträßer",
      "password": "test1234",
      "avatar": "https://robohash.org/asd213sd?set=set4",
      "ticketIds": [
        "1b49",
        "d2cf"
      ],
      "isadmin": true,
      "isloggedin": false,
      "id": 2
    },
    {
      "email": "david@mail.com",
      "fname": "David",
      "lname": "Brandenburg",
      "password": "test1234",
      "avatar": "https://robohash.org/da1234dsa?set=set4",
      "ticketIds": [
        "d3f1"
      ],
      "isadmin": true,
      "isloggedin": true,
      "id": 3
    },
    {
      "email": "test@mail.com",
      "fname": "Huge",
      "lname": "Cock",
      "password": "12345678",
      "avatar": "https://robohash.org/2zzk?set=set4",
      "ticketIds": [],
      "isadmin": false,
      "isloggedin": false,
      "id": 4
    },
    {
      "email": "Zwegat69@cock.com",
      "fname": "Peter",
      "lname": "Zwegat",
      "password": "hugecock123",
      "avatar": "/static/media/defaultProfilepic.b5d0704057147e38225a.webp",
      "ticketIds": [],
      "isadmin": false,
      "isloggedin": false,
      "id": 5
    },
    {
      "email": "cock123@web.de",
      "fname": "CumEater",
      "lname": "Cock",
      "password": "12345",
      "avatar": "https://robohash.org/ijnmlgjl?set=set4",
      "ticketIds": [],
      "isadmin": true,
      "isloggedin": false,
      "id": 6
    },
    {
      "email": "last1@mail.com",
      "fname": "test69",
      "lname": "69last",
      "password": "123",
      "avatar": "https://robohash.org/lz6368t?set=set4",
      "ticketIds": [],
      "isadmin": false,
      "isloggedin": false,
      "id": 7
    },
    {
      "email": "danny@cock.com",
      "fname": "testname1",
      "lname": "testname2",
      "password": "ichhabcock",
      "avatar": "https://robohash.org/byu9jvda?set=set4",
      "ticketIds": [],
      "isadmin": true,
      "isloggedin": false,
      "id": 8
    },
    {
      "email": "31231321@123.com",
      "fname": "123123123",
      "lname": "3232131231",
      "password": "1231231231223132",
      "avatar": "https://robohash.org/g9fkklc?set=set4",
      "ticketIds": [],
      "isadmin": false,
      "isloggedin": false,
      "id": 9
    }
  ],
  "tickets": [
    {
      "title": "Buuu",
      "desc": "fafasfasfaesefase",
      "status": "DONE",
      "deadline": "2024-02-29",
      "creator": "Danny",
      "editor": "Michelle",
      "editorId": "2",
      "editorAvatar": "https://robohash.org/asd213sd?set=set4",
      "id": "d2cf"
    },
    {
      "title": "test",
      "desc": "123",
      "status": "IN PROGRESS",
      "deadline": "2024-02-24",
      "creator": "David",
      "editor": "David",
      "editorId": "3",
      "editorAvatar": "https://robohash.org/da1234dsa?set=set4",
      "id": "uH2zfQ8"
    },
    {
      "title": "test123",
      "desc": "test",
      "status": "IN PROGRESS",
      "deadline": "2024-02-24",
      "creator": "Danny",
      "editor": "David",
      "editorId": "3",
      "editorAvatar": "https://robohash.org/da1234dsa?set=set4",
      "id": "3J6gWG4"
    },
    {
      "title": "test123",
      "desc": "test",
      "status": "IN REVIEW",
      "deadline": "2024-02-24",
      "creator": "Danny",
      "editor": "testname1",
      "editorId": "8",
      "editorAvatar": "https://robohash.org/byu9jvda?set=set4",
      "id": "P1oXUVz"
    },
    {
      "title": "test123",
      "desc": "test",
      "status": "IN PROGRESS",
      "deadline": "2024-02-24",
      "creator": "Danny",
      "editor": "David",
      "editorId": "3",
      "editorAvatar": "https://robohash.org/da1234dsa?set=set4",
      "id": "qmAmEZn"
    },
    {
      "title": "test123",
      "desc": "test",
      "status": "IN REVIEW",
      "deadline": "2024-02-24",
      "creator": "Danny",
      "editor": "CumEater",
      "editorId": "6",
      "editorAvatar": "https://robohash.org/ijnmlgjl?set=set4",
      "id": "ofcNxM9"
    },
    {
      "title": "das is ein test",
      "desc": "test test teest",
      "status": "TO DO",
      "deadline": "2024-02-28",
      "creator": "David",
      "editor": "David",
      "editorId": "3",
      "editorAvatar": "https://robohash.org/da1234dsa?set=set4",
      "id": "f2e5"
    },
    {
      "title": "testIdTEST",
      "desc": "123123123123123123",
      "status": "IN REVIEW",
      "deadline": "2024-02-23",
      "creator": "Danny",
      "editor": "Danny",
      "editorId": "1",
      "editorAvatar": "https://robohash.org/ph38?set=set4",
      "id": "OdBbzfo"
    }
  ]
}