{
  "tickets": [
    {
      "title": "test",
      "desc": "Lorem ipsum dolor, sit amet consectetur adipisicing elit. Cum delectus amet illum error neque maxime dolore labore sit, obcaecati assumenda vel maiores, odio minima blanditiis itaque. Consequatur totam quod quibusdam.",
      "status": "In progress..",
      "deadline": "TT:MM:JJJJ",
      "creator": 1,
      "id": 1
    }
  ],
  "users": [
    {
      "email": "danny@mail.com",
      "fname": "Danny",
      "lname": "Böhm",
      "password": "test1234",
      "avatar": "https://robohash.org/12313asda123155sdda?set=set4",
      "ticketId": [
        "1"
      ],
      "isadmin": true,
      "isloggedin": true,
      "id": 1
    },
    {
      "email": "michelle@mail.com",
      "fname": "Michelle",
      "lname": "Sträßer",
      "password": "test1234",
      "avatar": "https://robohash.org/asd213sd?set=set4",
      "ticketId": [],
      "isadmin": true,
      "isloggedin": false,
      "id": 2
    },
    {
      "email": "david@mail.com",
      "fname": "David",
      "lname": "Brandenburg",
      "password": "test1234",
      "avatar": "https://robohash.org/da1234dsa?set=set4",
      "ticketId": [],
      "isadmin": true,
      "isloggedin": false,
      "id": 3
    }
  ]
}